pshnb/__init__.py
pshnb/_modidx.py
pshnb/core.py
pshnb-0.0.2.dist-info/LICENSE
pshnb-0.0.2.dist-info/METADATA
pshnb-0.0.2.dist-info/WHEEL
pshnb-0.0.2.dist-info/entry_points.txt
pshnb-0.0.2.dist-info/top_level.txt
pshnb-0.0.2.dist-info/RECORD
