Metadata-Version: 2.1
Name: pshnb
Version: 0.0.2
Summary: AI magic
Home-page: https://github.com/answerdotai/pshnb
Author: Jeremy Howard
Author-email: info@answer.ai
License: Apache Software License 2.0
Keywords: nbdev jupyter notebook python bash
Classifier: Development Status :: 4 - Beta
Classifier: Intended Audience :: Developers
Classifier: License :: OSI Approved :: Apache Software License
Classifier: Natural Language :: English
Classifier: Programming Language :: Python :: 3.9
Classifier: Programming Language :: Python :: 3.10
Classifier: Programming Language :: Python :: 3.11
Classifier: Programming Language :: Python :: 3.12
Classifier: Programming Language :: Python :: 3.13
Requires-Python: >=3.9
License-File: LICENSE
Requires-Dist: pip
Requires-Dist: packaging
Requires-Dist: fastcore
Provides-Extra: dev
